wirecardpy/__init__.py
wirecardpy/models/__init__.py
wirecardpy/models/account.py
wirecardpy/models/anticipation.py
wirecardpy/models/balance.py
wirecardpy/models/bank_account.py
wirecardpy/models/notification.py
wirecardpy/models/order.py
wirecardpy/models/payment.py
wirecardpy/models/transfer.py
wirecardpy/utils/__init__.py
wirecardpy/utils/constants.py
wirecardpy/utils/util.py
wirecardpy-0.6.1.dist-info/LICENSE
wirecardpy-0.6.1.dist-info/METADATA
wirecardpy-0.6.1.dist-info/WHEEL
wirecardpy-0.6.1.dist-info/top_level.txt
wirecardpy-0.6.1.dist-info/RECORD
